django_subcommand2-0.1.1.dist-info/top_level.txt
django_subcommand2-0.1.1.dist-info/metadata.json
django_subcommand2-0.1.1.dist-info/RECORD
django_subcommand2-0.1.1.dist-info/WHEEL
django_subcommand2-0.1.1.dist-info/METADATA
django_subcommand2-0.1.1.dist-info/DESCRIPTION.rst
subcommand/__init__.py
subcommand/base.py
