Metadata-Version: 2.0
Name: django-subcommand2
Version: 0.1.1
Summary: Support subcommands in management commands
Home-page: https://github.com/CptLemming/django-subcommand2
Author: Ashley Wilson
Author-email: scifilem@gmail.com
License: BSD
Keywords: django-subcommand2
Platform: UNKNOWN
Classifier: Development Status :: 3 - Alpha
Classifier: Framework :: Django
Classifier: Framework :: Django :: 1.8
Classifier: Framework :: Django :: 1.9
Classifier: Intended Audience :: Developers
Classifier: License :: OSI Approved :: BSD License
Classifier: Natural Language :: English
Classifier: Programming Language :: Python :: 2
Classifier: Programming Language :: Python :: 2.7
Classifier: Programming Language :: Python :: 3
Classifier: Programming Language :: Python :: 3.3
Classifier: Programming Language :: Python :: 3.4
Classifier: Programming Language :: Python :: 3.5
